random_quotes_generator/__init__.py
random_quotes_generator/quotes.py
random_quotes_generator/quotes.txt
random_quotes_generator-0.1.0.dist-info/METADATA
random_quotes_generator-0.1.0.dist-info/WHEEL
random_quotes_generator-0.1.0.dist-info/RECORD
