Metadata-Version: 2.1
Name: random-quotes-generator
Version: 0.1.0
Summary: A Python package to generate random famous quotes for inspiration.
Author: Seun Fashina
Author-email: fashinaoluwaseun36@gmail.com
Requires-Python: >=3.10,<4.0
Classifier: Programming Language :: Python :: 3
Classifier: Programming Language :: Python :: 3.10
Classifier: Programming Language :: Python :: 3.11
